fpm_py/__init__.py
fpm_py/analysis/__init__.py
fpm_py/analysis/metrics.py
fpm_py/core/__init__.py
fpm_py/core/backward.py
fpm_py/core/forward.py
fpm_py/core/structs.py
fpm_py/utils/__init__.py
fpm_py/utils/data_utils.py
fpm_py/utils/math_utils.py
fpm_py-2.0.1.dist-info/licenses/LICENSE
fpm_py-2.0.1.dist-info/METADATA
fpm_py-2.0.1.dist-info/WHEEL
fpm_py-2.0.1.dist-info/top_level.txt
fpm_py-2.0.1.dist-info/RECORD
