Metadata-Version: 2.4
Name: fpm-py
Version: 2.0.1
Summary: Fourier ptychography tooling for simulation and reconstruction
Author-email: Robin Cunningham <rspcunningham@gmail.com>
License-Expression: MIT
Project-URL: Homepage, https://github.com/rspcunningham/fpm-py
Project-URL: Repository, https://github.com/rspcunningham/fpm-py
Project-URL: Issues, https://github.com/rspcunningham/fpm-py/issues
Keywords: fourier,ptychography,microscopy,imaging,reconstruction
Classifier: Development Status :: 3 - Alpha
Classifier: Intended Audience :: Science/Research
Classifier: Programming Language :: Python :: 3
Classifier: Programming Language :: Python :: 3.9
Classifier: Programming Language :: Python :: 3.10
Classifier: Programming Language :: Python :: 3.11
Classifier: Programming Language :: Python :: 3.12
Classifier: Topic :: Scientific/Engineering :: Image Processing
Requires-Python: <3.13,>=3.9
License-File: LICENSE
Requires-Dist: matplotlib>=3.9.4
Requires-Dist: scikit-image>=0.24.0
Requires-Dist: scipy>=1.13.1
Requires-Dist: seaborn>=0.13.2
Requires-Dist: torch>=2.8.0
Dynamic: license-file
